allinpay/__init__.py
allinpay/client/__init__.py
allinpay/client/base.py
allinpay/client/api/__init__.py
allinpay/client/api/base.py
allinpay/client/api/gateway.py
allinpay/client/api/posol.py
allinpay/client/api/prescanpay.py
allinpay/client/api/qpay.py
allinpay/client/api/tranx.py
allinpay/client/api/trxfile.py
allinpay/client/api/unitorder.py
allinpay/client/api/verify.py
allinpay/core/__init__.py
allinpay/core/exceptions.py
allinpay/core/utils.py
pyallinpay-1.1.10.dist-info/LICENSE
pyallinpay-1.1.10.dist-info/METADATA
pyallinpay-1.1.10.dist-info/WHEEL
pyallinpay-1.1.10.dist-info/top_level.txt
pyallinpay-1.1.10.dist-info/RECORD
